WordToNumber/__init__.py
WordToNumber/word_to_number.py
tests/__init__.py
tests/test_word_to_number.py
wordtonumber-1.1.0.dist-info/licenses/LICENSE
wordtonumber-1.1.0.dist-info/METADATA
wordtonumber-1.1.0.dist-info/WHEEL
wordtonumber-1.1.0.dist-info/top_level.txt
wordtonumber-1.1.0.dist-info/RECORD
