Metadata-Version: 2.4
Name: WordToNumber
Version: 1.1.0
Summary: A Python library for converting words to numbers.
Home-page: https://github.com/santoshvandari/WordToNumber
Author: Santosh Bhandari
Author-email: info@bhandari-santosh.com.np
License: MIT License
Keywords: word to number,number conversion,text processing
Classifier: Programming Language :: Python :: 3
Classifier: License :: OSI Approved :: MIT License
Classifier: Operating System :: OS Independent
Classifier: Intended Audience :: Developers
Classifier: Natural Language :: English
Classifier: Development Status :: 5 - Production/Stable
Classifier: Environment :: Console
Classifier: Topic :: Software Development :: Libraries :: Python Modules
License-File: LICENSE
Dynamic: author
Dynamic: author-email
Dynamic: classifier
Dynamic: description
Dynamic: description-content-type
Dynamic: home-page
Dynamic: keywords
Dynamic: license
Dynamic: license-file
Dynamic: summary
